{
  "LocalDebugUrl": "",
  "DevelopmentUrl": "",
  "StagingUrl": "",
  "ProductionUrl": "",
  "UpdatesDefinitionUrl": "",
  "RatingPrompt": {
    "Probability": 0.3333333,
    "AdditionalCount": 3,
    "AlwaysInclude": [
      {
        "Url": "",
        "Icon": "LogosGithub",
        "Labels": {
          "en": "Star on GitHub",
          "fr": "Mettre une étoile sur GitHub"
        }
      }
    ],
    "Stores": {
      "Windows": {
        "Url": "",
        "Icon": "RegularStore",
        "Labels": {
          "en": "Rate on Microsoft Store",
          "fr": "Noter sur Microsoft Store"
        }
      },
      "MacOs": {
        "Url": "",
        "Icon": "RegularStore",
        "Labels": {
          "en": "Rate on Mac App Store",
          "fr": "Noter sur Mac App Store"
        }
      }
    },
    "Additional": [
      {
        "Url": "",
        "Icon": "RegularWorld",
        "Labels": {
          "en": "Rate on AlternativeTo",
          "fr": "Noter sur AlternativeTo"
        }
      },
      {
        "Url": "",
        "Icon": "RegularWorld",
        "Labels": {
          "en": "Rate on MajorGeeks",
          "fr": "Noter sur MajorGeeks"
        }
      },
      {
        "Url": "",
        "Icon": "RegularWorld",
        "Labels": {
          "en": "Rate on Softpedia",
          "fr": "Noter sur Softpedia"
        }
      },
      {
        "Url": "",
        "Icon": "RegularWorld",
        "Labels": {
          "en": "Rate on Uptodown",
          "fr": "Noter sur Uptodown"
        }
      },
      {
        "Url": "",
        "Icon": "RegularWorld",
        "Labels": {
          "en": "Rate on SourceForge",
          "fr": "Noter sur SourceForge"
        }
      }
    ]
  }
}
